LICENSE
MANIFEST.in
redis-4.0.1.tar.gz
requirements.txt
setup.cfg
setup.py
open_redis/__init__.py
open_redis/deployment.py
open_redis/redis-base-config
open_redis/sentinel-base-config
open_redis.egg-info/PKG-INFO
open_redis.egg-info/SOURCES.txt
open_redis.egg-info/dependency_links.txt
open_redis.egg-info/entry_points.txt
open_redis.egg-info/requires.txt
open_redis.egg-info/top_level.txt
pyscripts/__init__.py
pyscripts/redis_express.py