Metadata-Version: 1.1
Name: open-redis
Version: 0.5
Summary: A python package to install and manage redis
Home-page: https://github.com/TheWiseLion/open-redis
Author: John Mecham
Author-email: jon.mecham@gmail.com
License: UNKNOWN
Keywords: redis,server,manager
Platform: UNKNOWN
Classifier: License :: OSI Approved :: BSD License
Classifier: Programming Language :: Python :: 2
Classifier: Programming Language :: Python :: 2.6
Classifier: Programming Language :: Python :: 2.7
Classifier: Programming Language :: Python :: 3
Classifier: Programming Language :: Python :: 3.3
Classifier: Programming Language :: Python :: 3.4
Classifier: Programming Language :: Python :: 3.5
Classifier: Programming Language :: Python :: 3.6
Classifier: Topic :: Software Development :: Libraries
Classifier: Topic :: Software Development :: Libraries :: Python Modules
Classifier: Topic :: System :: Systems Administration
Classifier: Topic :: Utilities
Classifier: Environment :: Console
